bgg/__init__.py
bgg/__main__.py
bgg/lib/__init__.py
bgg/lib/branches.py
bgg/lib/cleanup.py
bgg/lib/commit.py
bgg/lib/config.py
bgg/lib/getback.py
bgg/lib/makediff.py
bgg/lib/merge.py
bgg/lib/push.py
bgg/lib/rebase.py
bgg/lib/start.py
bgg/lib/state.py
bgg/lib/tags.py
bgg/lib/utils.py
bgg-0.24.1.data/scripts/G
bgg-0.24.1.dist-info/DESCRIPTION.rst
bgg-0.24.1.dist-info/METADATA
bgg-0.24.1.dist-info/metadata.json
bgg-0.24.1.dist-info/RECORD
bgg-0.24.1.dist-info/top_level.txt
bgg-0.24.1.dist-info/WHEEL
