Metadata-Version: 2.0
Name: bgg
Version: 0.24.1
Summary: A love story with Bugzilla, git and Github
Home-page: https://github.com/peterbe/bgg
Author: Peter Bengtsson
Author-email: mail@peterbe.com
License: MIT
Platform: UNKNOWN
Classifier: Development Status :: 4 - Beta
Classifier: Intended Audience :: Developers
Classifier: License :: OSI Approved :: MIT License
Classifier: Operating System :: OS Independent
Classifier: Programming Language :: Python
Classifier: Programming Language :: Python :: 2
Classifier: Programming Language :: Python :: 2.6
Classifier: Programming Language :: Python :: 2.7
